topsis/__init__.py
topsis/topsis.py
topsis_ikjot_102116071-0.0.1.dist-info/METADATA
topsis_ikjot_102116071-0.0.1.dist-info/WHEEL
topsis_ikjot_102116071-0.0.1.dist-info/top_level.txt
topsis_ikjot_102116071-0.0.1.dist-info/RECORD
