Metadata-Version: 2.1
Name: topsis-ikjot-102116071
Version: 0.0.1
Summary: TOPSIS Application
Author: Ikjot Singh
Author-email: <isingh_be21@thapar.edu>
Keywords: python,topsis
Classifier: Development Status :: 1 - Planning
Classifier: Intended Audience :: Developers
Classifier: Programming Language :: Python :: 3
Classifier: Operating System :: Unix
Classifier: Operating System :: MacOS :: MacOS X
Classifier: Operating System :: Microsoft :: Windows
Requires-Dist: sys
Requires-Dist: os
Requires-Dist: pandas
Requires-Dist: numpy
